mypythondb/__init__.py
mypythondb/console.py
mypythondb/mysession.py
mypythondb/queryprocessor.py
mypythondb/qwebserv.py
mypythondb-0.2.4.dist-info/LICENSE
mypythondb-0.2.4.dist-info/METADATA
mypythondb-0.2.4.dist-info/WHEEL
mypythondb-0.2.4.dist-info/entry_points.txt
mypythondb-0.2.4.dist-info/RECORD
