Metadata-Version: 2.1
Name: mypythondb
Version: 0.2.4
Summary: The MyPythonDB project
Home-page: https://github.com/ryanhamilton/pythondb
License: MIT
Keywords: hypermodern
Author: Ryan Hamilton
Requires-Python: >=3.9,<4.0
Classifier: License :: OSI Approved :: MIT License
Classifier: Programming Language :: Python :: 3
Classifier: Programming Language :: Python :: 3.9
Classifier: Programming Language :: Python :: 3.10
Classifier: Programming Language :: Python :: 3.11
Classifier: Programming Language :: Python :: 3.12
Requires-Dist: XlsxWriter (==3.2.0)
Requires-Dist: click (>=8.0,<9.0)
Requires-Dist: deltalake (>=0.18.2,<0.19.0)
Requires-Dist: desert (>=2020.1.6,<2021.0.0)
Requires-Dist: duckdb (==1.0.0)
Requires-Dist: kola (>=0.9.0,<0.10.0)
Requires-Dist: marshmallow (>=3.3.0,<4.0.0)
Requires-Dist: mysql_mimic (==2.5.5)
Requires-Dist: pandas (==2.2.2)
Requires-Dist: polars (==0.20.31)
Requires-Dist: pyarrow (==16.1.0)
Requires-Dist: requests (>=2.22.0,<3.0.0)
Project-URL: Documentation, https://github.com/ryanhamilton/pythondb
Project-URL: Repository, https://github.com/ryanhamilton/pythondb
